metalazero/__init__.py
metalazero-0.0.1.dist-info/LICENSE
metalazero-0.0.1.dist-info/METADATA
metalazero-0.0.1.dist-info/WHEEL
metalazero-0.0.1.dist-info/top_level.txt
metalazero-0.0.1.dist-info/RECORD
