Metadata-Version: 2.1
Name: metalazero
Version: 0.0.1
Summary: metalazero package
Home-page: https://github.com/james4deutschland/metalazero
Author: James Brown
Author-email: lazero@lazero.ltd
License: UNKNOWN
Project-URL: Bug Tracker, https://github.com/james4deustchland/metalazero/issues
Platform: UNKNOWN
Classifier: Programming Language :: Python :: 3
Classifier: License :: OSI Approved :: MIT License
Classifier: Operating System :: OS Independent
Requires-Python: >=3.6
